pgml_extension/__init__.py
pgml_extension/__main__.py
pgml_extension/datasets.py
pgml_extension/exceptions.py
pgml_extension/logging_setup.py
pgml_extension/model.py
pgml_extension/scratch.py
pgml_extension/sql.py
pgml_extension/transformers.py
pgml_extension/utils.py
pgml_extension/sql/install/models.sql
pgml_extension/sql/install/schema.sql
pgml_extension/sql/install/transformers.sql
pgml_extension/sql/install/vectors.sql
pgml_extension-1.0.1.dist-info/METADATA
pgml_extension-1.0.1.dist-info/WHEEL
pgml_extension-1.0.1.dist-info/top_level.txt
pgml_extension-1.0.1.dist-info/RECORD
