Metadata-Version: 2.1
Name: pgml-extension
Version: 1.0.1
Summary: Simple machine learning in PostgreSQL.
Home-page: https://github.com/postgresml/postgresml
Author: PostgresML Team
Author-email: maintainers@postgresml.org
Classifier: Programming Language :: Python :: 3
Classifier: Operating System :: OS Independent
Requires-Python: >=3.7
Requires-Dist: diptest
Requires-Dist: numpy
Requires-Dist: pandas
Requires-Dist: sklearn
Requires-Dist: xgboost
Requires-Dist: lightgbm
Requires-Dist: psycopg2
Requires-Dist: wheel
Requires-Dist: click
Requires-Dist: torch
Requires-Dist: transformers
Requires-Dist: datasets
Requires-Dist: sentencepiece
Requires-Dist: sacremoses
Requires-Dist: sacrebleu
Requires-Dist: rouge
Provides-Extra: dev
Requires-Dist: pytest ; extra == 'dev'
